rtl/traffic1.v
module traffic1(

    input clk,
    input rst,

    output reg AG,
    output reg AY,
    output reg AR,

    output reg BG,
    output reg BY,
    output reg BR
);
    reg [1:0] state;
    reg [1:0] next_state;

    parameter S0 = 2'b00; 
    parameter S1 = 2'b01; 
    parameter S2 = 2'b10; 
    parameter S3 = 2'b11;         

    always @(posedge clk or posedge rst) begin
        if (rst) begin
            state <= S0;
        end else begin
            state <= next_state;
        end
    end

    always @(*)
      begin
        case(state)

            S0: next_state = S1;
            S1: next_state = S2;
            S2: next_state = S3;
            S3: next_state = S0;

            default: next_state = S0;

        endcase
    end

    always @(*)
     begin
        AG = 0; AY = 0; AR = 0;
        BG = 0; BY = 0; BR = 0;

        case(state)

            S0:
            begin
                AG = 1;
                BR = 1;
             end

             S1:
            begin
                AY = 1;
                BR = 1;
            end

            S2:
            begin
                AR = 1;
                BG = 1;
            end

            S3:
            begin
                AR = 1;
                BY = 1;
            end

        endcase
    end
endmodule

tb/traffic1_tb.v
module traffic1_tb ();
    reg clk;
    reg rst;

    wire AG;
    wire AY;
    wire AR;

    wire BG;
    wire BY;
    wire BR;

    traffic1 uut (
        .clk(clk),
        .rst(rst),
        .AG(AG),
        .AY(AY),
        .AR(AR),
        .BG(BG),
        .BY(BY),
        .BR(BR)
    );

    initial begin
        clk = 0;
        forever #5 clk = ~clk; // 10ns clock period
    end

    initial begin
        $dumpfile("wave.vcd");
        $dumpvars(0, traffic1_tb);
        rst = 1; 
        #10 rst = 0;

        #100 $finish; 
    end
endmodule

wave.vcd
$date
	Tue Jun 16 14:35:47 2026
$end
$version
	Icarus Verilog
$end
$timescale
	1s
$end
$scope module traffic1_tb $end
$var wire 1 ! BY $end
$var wire 1 " BR $end
$var wire 1 # BG $end
$var wire 1 $ AY $end
$var wire 1 % AR $end
$var wire 1 & AG $end
$var reg 1 ' clk $end
$var reg 1 ( rst $end
$scope module uut $end
$var wire 1 ' clk $end
$var wire 1 ( rst $end
$var reg 1 & AG $end
$var reg 1 % AR $end
$var reg 1 $ AY $end
$var reg 1 # BG $end
$var reg 1 " BR $end
$var reg 1 ! BY $end
$var reg 2 ) next_state [1:0] $end
$var reg 2 * state [1:0] $end
$upscope $end
$upscope $end
$enddefinitions $end
#0
$dumpvars
b0 *
b1 )
1(
0'
1&
0%
0$
0#
1"
0!
$end
#5
1'
#10
0'
0(
#15
b10 )
1$
1"
0&
b1 *
1'
#20
0'
#25
1#
1%
0"
0$
b11 )
b10 *
1'
#30
0'
#35
b0 )
1!
0#
1%
b11 *
1'
#40
0'
#45
1"
1&
0!
0%
b1 )
b0 *
1'
#50
0'
#55
b10 )
1$
1"
0&
b1 *
1'
#60
0'
#65
1#
1%
0"
0$
b11 )
b10 *
1'
#70
0'
#75
b0 )
1!
0#
1%
b11 *
1'
#80
0'
#85
1"
1&
0!
0%
b1 )
b0 *
1'
#90
0'
#95
b10 )
1$
1"
0&
b1 *
1'
#100
0'
#105
1#
1%
0"
0$
b11 )
b10 *
1'
